MANIFEST.in
setup.py
xadmin/__init__.py
xadmin/__init__.pyc
xadmin/adminx.py
xadmin/adminx.pyc
xadmin/apps.py
xadmin/apps.pyc
xadmin/filters.py
xadmin/filters.pyc
xadmin/forms.py
xadmin/forms.pyc
xadmin/layout.py
xadmin/layout.pyc
xadmin/models.py
xadmin/models.pyc
xadmin/rselect.js
xadmin/rselect2.js
xadmin/sites.py
xadmin/sites.pyc
xadmin/util.py
xadmin/util.pyc
xadmin/vendors.py
xadmin/widgets.py
xadmin/widgets.pyc
xadmin/.tx/config
xadmin/__pycache__/__init__.cpython-36.pyc
xadmin/__pycache__/__init__.cpython-37.pyc
xadmin/__pycache__/adminx.cpython-36.pyc
xadmin/__pycache__/adminx.cpython-37.pyc
xadmin/__pycache__/apps.cpython-36.pyc
xadmin/__pycache__/apps.cpython-37.pyc
xadmin/__pycache__/filters.cpython-36.pyc
xadmin/__pycache__/filters.cpython-37.pyc
xadmin/__pycache__/forms.cpython-36.pyc
xadmin/__pycache__/forms.cpython-37.pyc
xadmin/__pycache__/layout.cpython-36.pyc
xadmin/__pycache__/layout.cpython-37.pyc
xadmin/__pycache__/models.cpython-36.pyc
xadmin/__pycache__/models.cpython-37.pyc
xadmin/__pycache__/sites.cpython-36.pyc
xadmin/__pycache__/sites.cpython-37.pyc
xadmin/__pycache__/util.cpython-36.pyc
xadmin/__pycache__/util.cpython-37.pyc
xadmin/__pycache__/vendors.cpython-36.pyc
xadmin/__pycache__/vendors.cpython-37.pyc
xadmin/__pycache__/widgets.cpython-36.pyc
xadmin/__pycache__/widgets.cpython-37.pyc
xadmin/css/xadmin.form.css
xadmin/css/xadmin.main.css
xadmin/css/xadmin.mobile.css
xadmin/css/xadmin.page.dashboard.css
xadmin/css/xadmin.plugin.aggregation.css
xadmin/css/xadmin.plugin.formset.css
xadmin/css/xadmin.plugin.quickfilter.css
xadmin/css/xadmin.plugins.css
xadmin/css/xadmin.responsive.css
xadmin/css/xadmin.widget.editable.css
xadmin/css/xadmin.widget.select-transfer.css
xadmin/css/themes/bootstrap-theme.css
xadmin/css/themes/bootstrap-theme.min.css
xadmin/css/themes/bootstrap-xadmin.css
xadmin/js/xadmin.main.js
xadmin/js/xadmin.page.dashboard.js
xadmin/js/xadmin.page.form.js
xadmin/js/xadmin.page.list.js
xadmin/js/xadmin.plugin.actions.js
ym_xadmin.egg-info/PKG-INFO
ym_xadmin.egg-info/SOURCES.txt
ym_xadmin.egg-info/dependency_links.txt
ym_xadmin.egg-info/top_level.txt