Metadata-Version: 1.0
Name: ym-xadmin
Version: 0.0.5
Summary: xadmin for python3
Home-page: https://github.com/LiangjunFeng/SICA
Author: UNKNOWN
Author-email: UNKNOWN
License: MIT Licence
Keywords: pip,python3,xadmin
Platform: any
